mcycle/DEFAULTS.py
mcycle/__init__.py
mcycle/bases/__init__.py
mcycle/bases/component.py
mcycle/bases/config.py
mcycle/bases/cycle.py
mcycle/bases/flowstate.py
mcycle/bases/flowstatepoly.py
mcycle/bases/geom.py
mcycle/bases/mcabstractbase.py
mcycle/bases/methods.py
mcycle/bases/solidmaterial.py
mcycle/components/__init__.py
mcycle/components/compressors/__init__.py
mcycle/components/compressors/comp_basic.py
mcycle/components/coolers/__init__.py
mcycle/components/coolers/clr_basic.py
mcycle/components/expanders/__init__.py
mcycle/components/expanders/exp_basic.py
mcycle/components/heaters/__init__.py
mcycle/components/heaters/htr_basic.py
mcycle/components/hxs/__init__.py
mcycle/components/hxs/hx_basic.py
mcycle/components/hxs/hx_basicplanar.py
mcycle/components/hxs/hx_plate.py
mcycle/components/hxs/hxunits/__init__.py
mcycle/components/hxs/hxunits/hxunit_basic.py
mcycle/components/hxs/hxunits/hxunit_basiccylinder.py
mcycle/components/hxs/hxunits/hxunit_basicplanar.py
mcycle/components/hxs/hxunits/hxunit_plate.py
mcycle/cycles/__init__.py
mcycle/cycles/rankinebasic.py
mcycle/geometries/__init__.py
mcycle/geometries/geom_hxplate.py
mcycle/library/__init__.py
mcycle/library/compressible_flow_relations.py
mcycle/library/conversions.py
mcycle/library/heat_exchangers.py
mcycle/library/heat_transfer_methods.py
mcycle/library/materials.py
mcycle/library/standard_atmospheres.py
mcycle-0.1.3.dist-info/DESCRIPTION.rst
mcycle-0.1.3.dist-info/METADATA
mcycle-0.1.3.dist-info/RECORD
mcycle-0.1.3.dist-info/WHEEL
mcycle-0.1.3.dist-info/dependency_links.txt
mcycle-0.1.3.dist-info/metadata.json
mcycle-0.1.3.dist-info/top_level.txt
tests/__init__.py
tests/test_CompBasic.py
tests/test_Component.py
tests/test_DEFAULTS.py
tests/test_ExpBasic.py
tests/test_FlowState.py
tests/test_HtrBasic.py
tests/test_HxPlate.py
tests/test_HxUnitBasic.py
tests/test_HxUnitPlate.py
tests/test_Methods.py
tests/test_RankineBasic.py
