Metadata-Version: 2.0
Name: mcycle
Version: 0.1.3
Summary: Power cycle sizing and analysis package
Home-page: https://github.com/momargoh/MCycle
Author: Momar Hughes
Author-email: momar.hughes@unsw.edu.au
License: Apache License 2.0
Keywords: thermodynamics organic Rankine cycle power cycle evaporator expander condenser compressor heat exchanger heater cooler
Platform: UNKNOWN
Classifier: Development Status :: 3 - Alpha
Classifier: Intended Audience :: Developers
Classifier: Intended Audience :: Education
Classifier: Intended Audience :: Science/Research
Classifier: License :: OSI Approved :: Apache Software License
Classifier: Natural Language :: English
Classifier: Operating System :: OS Independent
Classifier: Programming Language :: Python :: 3 :: Only
Classifier: Topic :: Education
Classifier: Topic :: Scientific/Engineering
Classifier: Topic :: Scientific/Engineering :: Chemistry
Classifier: Topic :: Scientific/Engineering :: Physics
Requires-Python: >=3
Requires-Dist: CoolProp
Requires-Dist: matplotlib
Requires-Dist: numpy
Requires-Dist: scipy
